frappe_manager/__init__.py
frappe_manager/commands.py
frappe_manager/compose_manager/ComposeFile.py
frappe_manager/compose_manager/__init__.py
frappe_manager/compose_manager/compose_file_exceptions.py
frappe_manager/compose_project/compose_project.py
frappe_manager/compose_project/exceptions.py
frappe_manager/display_manager/DisplayManager.py
frappe_manager/docker_wrapper/DockerClient.py
frappe_manager/docker_wrapper/DockerCompose.py
frappe_manager/docker_wrapper/DockerException.py
frappe_manager/docker_wrapper/__init__.py
frappe_manager/docker_wrapper/subprocess_output.py
frappe_manager/images-tag.json
frappe_manager/logger/__init__.py
frappe_manager/logger/log.py
frappe_manager/main.py
frappe_manager/metadata_manager.py
frappe_manager/migration_manager/__init__.py
frappe_manager/migration_manager/backup_manager.py
frappe_manager/migration_manager/base_templates/docker-compose.services.osx.tmpl
frappe_manager/migration_manager/base_templates/docker-compose.services.tmpl
frappe_manager/migration_manager/base_templates/docker-compose.tmpl
frappe_manager/migration_manager/migration_base.py
frappe_manager/migration_manager/migration_exections.py
frappe_manager/migration_manager/migration_executor.py
frappe_manager/migration_manager/migration_helpers.py
frappe_manager/migration_manager/migrations/__init__.py
frappe_manager/migration_manager/migrations/migrate_0_10_0.py
frappe_manager/migration_manager/migrations/migrate_0_11_0.py
frappe_manager/migration_manager/migrations/migrate_0_12_0.py
frappe_manager/migration_manager/migrations/migrate_0_13_0.py
frappe_manager/migration_manager/migrations/migrate_0_13_1.py
frappe_manager/migration_manager/migrations/migrate_0_14_0.py
frappe_manager/migration_manager/migrations/migrate_0_15_0.py
frappe_manager/migration_manager/migrations/migrate_0_17_0.py
frappe_manager/migration_manager/migrations/migrate_0_18_0.py
frappe_manager/migration_manager/migrations/migrate_0_9_0.py
frappe_manager/migration_manager/version.py
frappe_manager-0.18.0.dist-info/LICENSE
frappe_manager-0.18.0.dist-info/METADATA
frappe_manager-0.18.0.dist-info/WHEEL
frappe_manager-0.18.0.dist-info/entry_points.txt
frappe_manager-0.18.0.dist-info/RECORD
