Metadata-Version: 2.1
Name: frappe-manager
Version: 0.18.0
Summary: A CLI tool based on Docker Compose to easily manage Frappe based projects. As of now, only suitable for development in local machines running on Mac and Linux based OS.
Home-page: https://github.com/rtcamp/frappe-manager
License: MIT
Author: rtCamp
Author-email: sys@rtcamp.com
Maintainer: Alok Singh
Maintainer-email: alok.singh@rtcamp.com
Requires-Python: >=3.10,<4.0
Classifier: License :: OSI Approved :: MIT License
Classifier: Programming Language :: Python :: 3
Classifier: Programming Language :: Python :: 3.10
Classifier: Programming Language :: Python :: 3.11
Classifier: Programming Language :: Python :: 3.12
Requires-Dist: certbot (>=2.9.0,<3.0.0)
Requires-Dist: certbot-dns-cloudflare (>=2.10.0,<3.0.0)
Requires-Dist: configargparse (!=1.7)
Requires-Dist: email-validator (>=2.1.1,<3.0.0)
Requires-Dist: inquirerpy (>=0.3.4,<0.4.0)
Requires-Dist: jinja2 (>=3.1.3,<4.0.0)
Requires-Dist: ngrok (>=1.4.0,<2.0.0)
Requires-Dist: passlib (>=1.7.4,<2.0.0)
Requires-Dist: psutil (>=5.9.6,<6.0.0)
Requires-Dist: pydantic (>=2.6.4,<3.0.0)
Requires-Dist: requests (>=2.31.0,<3.0.0)
Requires-Dist: ruamel-yaml (>=0.18.5,<0.19.0)
Requires-Dist: tomlkit (>=0.12.3,<0.13.0)
Requires-Dist: typer (>=0.15.4,<0.16.0)
Project-URL: Bug Tracker, https://github.com/rtcamp/frappe-manager/issues
Project-URL: Documentation, https://github.com/rtcamp/frappe-manager/wiki
Project-URL: Repository, https://github.com/rtcamp/frappe-manager
